fairseq/__init__.py
fairseq/data/__init__.py
fairseq/data/data_utils.py
fairseq/data/dictionary.py
fairseq/dataclass/__init__.py
fairseq/dataclass/configs.py
fairseq/dataclass/constants.py
fairseq/dataclass/initialize.py
fairseq/dataclass/utils.py
fairseq/file_chunker_utils.py
fairseq/file_io.py
fairseq/incremental_decoding_utils.py
fairseq/models/__init__.py
fairseq/models/bart/__init__.py
fairseq/models/bart/hub_interface.py
fairseq/models/bart/model.py
fairseq/models/composite_encoder.py
fairseq/models/distributed_fairseq_model.py
fairseq/models/ema/__init__.py
fairseq/models/ema/ema.py
fairseq/models/fairseq_decoder.py
fairseq/models/fairseq_encoder.py
fairseq/models/fairseq_incremental_decoder.py
fairseq/models/fairseq_model.py
fairseq/models/fconv.py
fairseq/models/fconv_lm.py
fairseq/models/fconv_self_att.py
fairseq/models/hubert/__init__.py
fairseq/models/hubert/hubert.py
fairseq/models/hubert/hubert_asr.py
fairseq/models/huggingface/__init__.py
fairseq/models/huggingface/hf_gpt2.py
fairseq/models/lightconv.py
fairseq/models/lightconv_lm.py
fairseq/models/lstm.py
fairseq/models/lstm_lm.py
fairseq/models/masked_lm.py
fairseq/models/model_utils.py
fairseq/models/multilingual_transformer.py
fairseq/models/multires_hubert/__init__.py
fairseq/models/multires_hubert/multires_hubert.py
fairseq/models/multires_hubert/multires_hubert_asr.py
fairseq/models/nat/__init__.py
fairseq/models/nat/cmlm_transformer.py
fairseq/models/nat/fairseq_nat_model.py
fairseq/models/nat/insertion_transformer.py
fairseq/models/nat/iterative_nonautoregressive_transformer.py
fairseq/models/nat/levenshtein_transformer.py
fairseq/models/nat/levenshtein_utils.py
fairseq/models/nat/nat_crf_transformer.py
fairseq/models/nat/nonautoregressive_ensembles.py
fairseq/models/nat/nonautoregressive_transformer.py
fairseq/models/roberta/__init__.py
fairseq/models/roberta/alignment_utils.py
fairseq/models/roberta/enc_dec.py
fairseq/models/roberta/hub_interface.py
fairseq/models/roberta/model.py
fairseq_light-0.2.0.dist-info/METADATA
fairseq_light-0.2.0.dist-info/WHEEL
fairseq_light-0.2.0.dist-info/RECORD
