Metadata-Version: 2.3
Name: fairseq-light
Version: 0.2.0
Summary: 
Author: migo
Author-email: 1695587905@qq.com
Requires-Python: >=3.10,<3.13
Classifier: Programming Language :: Python :: 3
Classifier: Programming Language :: Python :: 3.10
Classifier: Programming Language :: Python :: 3.11
Classifier: Programming Language :: Python :: 3.12
Requires-Dist: numpy (<2.3)
Requires-Dist: omegaconf
Requires-Dist: scipy (<1.16)
Requires-Dist: tqdm
